pdns_zone_search/__init__.py
pdns_zone_search/main.py
pdns_zone_search-1.0.25.dist-info/entry_points.txt
pdns_zone_search-1.0.25.dist-info/licenses/LICENSE
pdns_zone_search-1.0.25.dist-info/WHEEL
pdns_zone_search-1.0.25.dist-info/METADATA
pdns_zone_search-1.0.25.dist-info/RECORD
