Metadata-Version: 2.4
Name: pdns-zone-search
Version: 1.0.25
Summary: CLI tool for searching PowerDNS zone listings
Author-email: Captain Wulfstar <9593988-wulf-star@users.noreply.gitlab.com>
Requires-Python: >=3.6
Classifier: Programming Language :: Python :: 3
Classifier: License :: OSI Approved :: MIT License
Classifier: Operating System :: OS Independent
License-File: LICENSE
Requires-Dist: pytest>=6.0 ; extra == "dev"
Requires-Dist: pytest-cov>=2.12.0 ; extra == "dev"
Requires-Dist: bumpver ; extra == "dev"
Project-URL: Bug Tracker, https://gitlab.com/wulfstar-com/pdns-zone-search/-/issues
Project-URL: Home Page, https://gitlab.com/wulfstar-com/pdns-zone-search
Project-URL: Source Code, https://gitlab.com/wulfstar-com/pdns-zone-search
Provides-Extra: dev
